pydatomic/.DS_Store
pydatomic/__init__.py
pydatomic/builtin.py
pydatomic/core.py
pydatomic/exceptions.py
pydatomic/facts.py
pydatomic/util.py
pydatomic-0.1.5.dist-info/WHEEL
pydatomic-0.1.5.dist-info/METADATA
pydatomic-0.1.5.dist-info/licenses/LICENSE.md
pydatomic-0.1.5.dist-info/RECORD
